{
    "ProviderList":  [
                         {
                             "ProviderGUID":  "7da2787c-62d1-4f99-939e-11b60c3aa761",
                             "ProviderName":  "Microsoft.Windows.DriverStore",
                             "ProviderGroupGUID":  "4f50731a-89cf-4782-b3e0-dce8c90476ba"
                         },
                         {
                             "ProviderGUID":  "059a2460-1077-115e-bdeb-5221de48b9e4",
                             "ProviderName":  "Microsoft.Windows.DriverStore.DriverPackage",
                             "ProviderGroupGUID":  "4f50731a-89cf-4782-b3e0-dce8c90476ba"
                         }
                     ],
    "EventList":  [
                      {
                          "EventID":  0,
                          "Channel":  11,
                          "Level":  5,
                          "Opcode":  0,
                          "Keyword":  35184372088832,
                          "KeywordName":  "MS.TELEMETRY",
                          "Extension":  [
                                            0
                                        ],
                          "EventName":  "DriverPackage.FileCorruption",
                          "Fields":  [
                                         {
                                             "FieldName":  "PartA_PrivTags",
                                             "InType":  "UINT64",
                                             "OutType":  "",
                                             "Extension":  null,
                                             "ValueCount":  0,
                                             "TypeInfo":  ""
                                         },
                                         {
                                             "FieldName":  "DriverPackageId",
                                             "InType":  "UNICODESTRING",
                                             "OutType":  "",
                                             "Extension":  null,
                                             "ValueCount":  0,
                                             "TypeInfo":  ""
                                         },
                                         {
                                             "FieldName":  "Discrepancies",
                                             "InType":  "STRUCT",
                                             "OutType":  "HEX",
                                             "Extension":  null,
                                             "ValueCount":  0,
                                             "TypeInfo":  ""
                                         },
                                         {
                                             "FieldName":  "DriverFile",
                                             "InType":  "COUNTEDSTRING",
                                             "OutType":  "",
                                             "Extension":  null,
                                             "ValueCount":  0,
                                             "TypeInfo":  ""
                                         },
                                         {
                                             "FieldName":  "Expected",
                                             "InType":  "COUNTEDSTRING",
                                             "OutType":  "",
                                             "Extension":  null,
                                             "ValueCount":  0,
                                             "TypeInfo":  ""
                                         },
                                         {
                                             "FieldName":  "Actual",
                                             "InType":  "COUNTEDSTRING",
                                             "OutType":  "",
                                             "Extension":  null,
                                             "ValueCount":  0,
                                             "TypeInfo":  ""
                                         },
                                         {
                                             "FieldName":  "Flags",
                                             "InType":  "INT32",
                                             "OutType":  "",
                                             "Extension":  null,
                                             "ValueCount":  0,
                                             "TypeInfo":  ""
                                         }
                                     ]
                      },
                      {
                          "EventID":  0,
                          "Channel":  11,
                          "Level":  5,
                          "Opcode":  0,
                          "Keyword":  70368744177664,
                          "KeywordName":  "MS.MEASURES",
                          "Extension":  [
                                            0
                                        ],
                          "EventName":  "InfParser",
                          "Fields":  [
                                         {
                                             "FieldName":  "DriverInfName",
                                             "InType":  "UNICODESTRING",
                                             "OutType":  "",
                                             "Extension":  null,
                                             "ValueCount":  0,
                                             "TypeInfo":  ""
                                         },
                                         {
                                             "FieldName":  "ProcessorArchitecture",
                                             "InType":  "UINT16",
                                             "OutType":  "",
                                             "Extension":  null,
                                             "ValueCount":  0,
                                             "TypeInfo":  ""
                                         },
                                         {
                                             "FieldName":  "LanguageId",
                                             "InType":  "UINT32",
                                             "OutType":  "",
                                             "Extension":  null,
                                             "ValueCount":  0,
                                             "TypeInfo":  ""
                                         },
                                         {
                                             "FieldName":  "ClassGuid",
                                             "InType":  "GUID",
                                             "OutType":  "",
                                             "Extension":  null,
                                             "ValueCount":  0,
                                             "TypeInfo":  ""
                                         },
                                         {
                                             "FieldName":  "Flags",
                                             "InType":  "UINT32",
                                             "OutType":  "",
                                             "Extension":  null,
                                             "ValueCount":  0,
                                             "TypeInfo":  ""
                                         },
                                         {
                                             "FieldName":  "DriverProvider",
                                             "InType":  "UNICODESTRING",
                                             "OutType":  "",
                                             "Extension":  null,
                                             "ValueCount":  0,
                                             "TypeInfo":  ""
                                         },
                                         {
                                             "FieldName":  "DriverDate",
                                             "InType":  "UNICODESTRING",
                                             "OutType":  "",
                                             "Extension":  null,
                                             "ValueCount":  0,
                                             "TypeInfo":  ""
                                         },
                                         {
                                             "FieldName":  "DriverVersion",
                                             "InType":  "UNICODESTRING",
                                             "OutType":  "",
                                             "Extension":  null,
                                             "ValueCount":  0,
                                             "TypeInfo":  ""
                                         },
                                         {
                                             "FieldName":  "InfErrorCodes",
                                             "InType":  "UINT16",
                                             "OutType":  "",
                                             "Extension":  null,
                                             "ValueCount":  0,
                                             "TypeInfo":  ""
                                         },
                                         {
                                             "FieldName":  "ReturnCode",
                                             "InType":  "UINT32",
                                             "OutType":  "WIN32ERROR",
                                             "Extension":  null,
                                             "ValueCount":  0,
                                             "TypeInfo":  ""
                                         }
                                     ]
                      }
                  ],
    "FilePath":  "C:\\Windows\\WinSxS\\x86_microsoft-windows-servicingstack_31bf3856ad364e35_10.0.26100.2890_none_48e069d5bf0c17cb\\drvstore.dll"
}